lerobot_teleoperator_bi_so101_leader/__init__.py
lerobot_teleoperator_bi_so101_leader/bi_so101_leader.py
lerobot_teleoperator_bi_so101_leader/config_bi_so101_leader.py
lerobot_teleoperator_bi_so101_leader-0.0.9.dist-info/licenses/LICENSE
lerobot_teleoperator_bi_so101_leader-0.0.9.dist-info/METADATA
lerobot_teleoperator_bi_so101_leader-0.0.9.dist-info/WHEEL
lerobot_teleoperator_bi_so101_leader-0.0.9.dist-info/top_level.txt
lerobot_teleoperator_bi_so101_leader-0.0.9.dist-info/RECORD
